README.md
setup.py
embedchain/__init__.py
embedchain/embedchain.py
embedchain/utils.py
embedchain/chunkers/__init__.py
embedchain/chunkers/base_chunker.py
embedchain/chunkers/pdf_file.py
embedchain/chunkers/qna_pair.py
embedchain/chunkers/text.py
embedchain/chunkers/web_page.py
embedchain/chunkers/youtube_video.py
embedchain/loaders/__init__.py
embedchain/loaders/local_qna_pair.py
embedchain/loaders/local_text.py
embedchain/loaders/pdf_file.py
embedchain/loaders/web_page.py
embedchain/loaders/youtube_video.py
embedchain/vectordb/__init__.py
embedchain/vectordb/base_vector_db.py
embedchain/vectordb/chroma_db.py
embedchain_harin.egg-info/PKG-INFO
embedchain_harin.egg-info/SOURCES.txt
embedchain_harin.egg-info/dependency_links.txt
embedchain_harin.egg-info/requires.txt
embedchain_harin.egg-info/top_level.txt