Metadata-Version: 2.1
Name: embedchain-harin
Version: 1.0.1
Summary: embedchain is a framework to easily create LLM powered bots over any dataset
Home-page: https://github.com/harin329/embedchain
Author: Harin Wu
Author-email: harinwu99@gmail.com
License: UNKNOWN
Platform: UNKNOWN
Classifier: Programming Language :: Python :: 3
Classifier: License :: OSI Approved :: Apache Software License
Classifier: Operating System :: OS Independent
Requires-Python: >=3.8
